{
  "2026-07-06": {
    "idx": 1,
    "stage": 2,
    "stage_name": "②编程一期",
    "diff": 1,
    "theme": "倒推法",
    "q": "小明有一些糖果，第一天吃掉一半多 2 颗，第二天吃掉剩下的一半多 1 颗，还剩 5 颗。小明原来有多少颗糖果？",
    "sol": "**逆向思维**：从结果往前推。\n- 第三天剩 5 颗 → 第二天吃完前有：5×2+1 = **11 颗**\n- 第二天剩 11 颗 → 第一天吃完前有：11×2+2 = **24 颗**\n\n**答：原来有 24 颗糖果。**",
    "v1": "修路问题：某工程队修路，第一天修了全长的一半多 50 米，第二天修了剩下的一半多 20 米，还剩 80 米。全长多少米？",
    "v1a": "**(80+20)×2+50 = 250 米**",
    "v2": "小华有一些零花钱，第一天花掉一半多 3 元，第二天又花掉剩下的一半多 1 元，最后剩 8 元。原来有多少钱？",
    "v2a": "**(8+1)×2+3 = 21 元**"
  },
  "2026-07-07": {
    "idx": 2,
    "stage": 2,
    "stage_name": "②编程一期",
    "diff": 1,
    "theme": "和差",
    "q": "妈妈买苹果和梨共 20 个，苹果比梨多 4 个，问苹果和梨各多少个？",
    "sol": "**和差问题**：(和+差)÷2 = 较大数\n- 苹果：(20+4)÷2 = **12 个**\n- 梨：20-12 = **8 个**\n\n**答：苹果 12 个，梨 8 个。**",
    "v1": "两筐水果共 50 斤，第一筐比第二筐多 10 斤，两筐各多少斤？",
    "v1a": "**第一筐 30 斤，第二筐 20 斤**",
    "v2": "小红和小明共有 30 张邮票，小红比小明多 6 张，两人各多少张？",
    "v2a": "**小红 18 张，小明 12 张**"
  },
  "2026-07-08": {
    "idx": 3,
    "stage": 2,
    "stage_name": "②编程一期",
    "diff": 1,
    "theme": "倒推+等量",
    "q": "甲乙两人共有铅笔 36 支，甲给乙 4 支后两人同样多。问甲乙原来各多少支？",
    "sol": "**关键**：甲给乙 4 支后相等 → 甲比乙多 8 支。\n- 甲：(36+8)÷2 = **22 支**\n- 乙：36-22 = **14 支**\n\n**验证**：甲给乙 4 支 → 甲 18，乙 18 ✓\n\n**答：甲 22 支，乙 14 支。**",
    "v1": "甲乙共有图书 50 本，甲给乙 6 本后两人相等，原各多少？",
    "v1a": "**甲 31 本，乙 19 本**",
    "v2": "两袋糖共 40 颗，从甲袋拿出 5 颗给乙袋后相等，原各多少？",
    "v2a": "**甲 25 颗，乙 15 颗**"
  },
  "2026-07-09": {
    "idx": 4,
    "stage": 2,
    "stage_name": "②编程一期",
    "diff": 1,
    "theme": "和差",
    "q": "两个数的和是 50，差是 10，求这两个数。",
    "sol": "**公式**：(和+差)÷2 = 大数，(和-差)÷2 = 小数\n- 大数：(50+10)÷2 = **30**\n- 小数：(50-10)÷2 = **20**\n\n**答：两数是 30 和 20。**",
    "v1": "父子年龄和是 50 岁，差是 26 岁，父子各几岁？",
    "v1a": "**父 38 岁，子 12 岁**",
    "v2": "长方形周长 36 米，长比宽多 6 米，长宽各多少米？",
    "v2a": "**长 12 米，宽 6 米**"
  },
  "2026-07-10": {
    "idx": 5,
    "stage": 2,
    "stage_name": "②编程一期",
    "diff": 1,
    "theme": "等量代换",
    "q": "1 个苹果 + 1 个梨 = 300 克，1 个苹果 + 2 个梨 = 400 克，问 1 个梨多少克？",
    "sol": "**关键**：两式相减得 1 个梨。\n- 400 - 300 = 100 克 = 1 个梨\n- 苹果：300 - 100 = 200 克\n\n**答：1 个梨 100 克，1 个苹果 200 克。**",
    "v1": "1 支钢笔 + 1 支铅笔 = 18 元，1 支钢笔 + 3 支铅笔 = 30 元，钢笔铅笔各多少？",
    "v1a": "**钢笔 12 元，铅笔 6 元**",
    "v2": "2 杯水 + 1 瓶水 = 700 毫升，1 杯水 + 1 瓶水 = 500 毫升，1 杯多少毫升？",
    "v2a": "**1 杯 200 毫升**"
  },
  "2026-07-11": {
    "idx": 6,
    "stage": 2,
    "stage_name": "②编程一期",
    "diff": 1,
    "theme": "和差",
    "q": "甲班比乙班多 8 人，两班共 92 人，甲乙两班各多少人？",
    "sol": "**和差问题**：(和-差)÷2 = 较小数\n- 乙班：(92-8)÷2 = **42 人**\n- 甲班：42+8 = **50 人**\n\n**答：甲班 50 人，乙班 42 人。**",
    "v1": "哥哥比弟弟大 5 岁，兄弟俩年龄和 25 岁，两人各几岁？",
    "v1a": "**哥 15 岁，弟 10 岁**",
    "v2": "两堆煤共 120 吨，第一堆比第二堆多 20 吨，各多少？",
    "v2a": "**第一堆 70 吨，第二堆 50 吨**"
  },
  "2026-07-12": {
    "idx": 7,
    "stage": 2,
    "stage_name": "②编程一期",
    "diff": 1,
    "theme": "倒推",
    "q": "一筐苹果，先卖出一半多 3 个，又卖出剩下的一半多 1 个，最后剩 4 个。原来有多少？",
    "sol": "**倒推法**（分步往前推）：\n- 最后剩 4 个 → 第二次卖前：4×2+1 = 9 个\n- 第二次卖前 9 个 → 第一次卖前：9×2+3 = 21 个\n\n**答：原来有 21 个苹果。**",
    "v1": "水池有水，先放出 1/3 多 5 吨，又放出剩下 1/2 多 3 吨，剩 8 吨。原有多少？",
    "v1a": "**原有 33 吨**",
    "v2": "一袋糖分给小朋友，先分一半多 2 颗，又分剩下的一半多 1 颗，最后剩 3 颗。原有多少？",
    "v2a": "**原有 15 颗**"
  },
  "2026-07-13": {
    "idx": 8,
    "stage": 2,
    "stage_name": "②编程一期",
    "diff": 1,
    "theme": "和差",
    "q": "姐姐和妹妹共有压岁钱 800 元，姐姐比妹妹多 200 元，两人各多少元？",
    "sol": "**和差**：\n- 姐姐：(800+200)÷2 = **500 元**\n- 妹妹：800-500 = **300 元**\n\n**答：姐姐 500 元，妹妹 300 元。**",
    "v1": "果园有桃树和梨树共 240 棵，桃树比梨树多 40 棵，两种树各多少？",
    "v1a": "**桃树 140，梨树 100**",
    "v2": "甲乙两仓共存粮 500 吨，甲比乙多 80 吨，各存多少？",
    "v2a": "**甲 290 吨，乙 210 吨**"
  },
  "2026-07-14": {
    "idx": 9,
    "stage": 2,
    "stage_name": "②编程一期",
    "diff": 1,
    "theme": "倒推",
    "q": "小亮有一些邮票，送给小张一半多 3 张，又送给小林剩下的一半多 1 张，最后剩 5 张。原来多少？",
    "sol": "**逐步倒推**：\n- 最后剩 5 → 送小林前：5×2+1 = 11 张\n- 送小林前 11 → 送小张前：11×2+3 = 25 张\n\n**答：原来有 25 张邮票。**",
    "v1": "一袋大米，先吃 1/2 多 5 斤，又吃剩下 1/3 多 2 斤，剩 6 斤。原有几斤？",
    "v1a": "**原有 24 斤**",
    "v2": "小明有铅笔，分给同学一半多 2 支，又分剩下的一半多 1 支，剩 3 支。原有几支？",
    "v2a": "**原有 15 支**"
  },
  "2026-07-15": {
    "idx": 10,
    "stage": 2,
    "stage_name": "②编程一期",
    "diff": 1,
    "theme": "和差",
    "q": "甲乙两人共存款 1500 元，甲比乙多 300 元，甲乙各多少？",
    "sol": "**和差**：(1500+300)÷2 = 900，(1500-300)÷2 = 600\n\n**答：甲 900 元，乙 600 元。**",
    "v1": "一个长方形周长 60 cm，长比宽多 8 cm，长宽各多少？",
    "v1a": "**长 19 cm，宽 11 cm**",
    "v2": "甲乙共有图书 100 本，甲比乙多 30 本，各多少？",
    "v2a": "**甲 65 本，乙 35 本**"
  },
  "2026-07-16": {
    "idx": 11,
    "stage": 2,
    "stage_name": "②编程一期",
    "diff": 1,
    "theme": "等量代换",
    "q": "2 支圆珠笔 = 1 支钢笔，1 支钢笔 + 1 支圆珠笔 = 18 元，问 1 支钢笔多少元？",
    "sol": "**代入**：1 支钢笔 = 2 支圆珠笔 → 2 支圆珠笔+1 支圆珠笔 = 3 支圆珠笔 = 18 元\n- 圆珠笔：18÷3 = 6 元\n- 钢笔：6×2 = 12 元\n\n**答：1 支钢笔 12 元。**",
    "v1": "3 个苹果 = 2 个梨，2 个苹果 + 1 个梨 = 16 元，1 个苹果多少元？",
    "v1a": "**1 个苹果 4 元**",
    "v2": "1 头牛 = 2 匹马，1 头牛 + 1 匹马 = 8000 元，1 头牛多少元？",
    "v2a": "**1 头牛 5333 元（约）**"
  },
  "2026-07-17": {
    "idx": 12,
    "stage": 2,
    "stage_name": "②编程一期",
    "diff": 1,
    "theme": "综合",
    "q": "两数之和为 36，差为 12，求这两个数。",
    "sol": "**和差**：(36+12)÷2 = 24，(36-12)÷2 = 12\n\n**答：24 和 12。**",
    "v1": "两数之和 50，差 10，求两数。",
    "v1a": "**30 和 20**",
    "v2": "两数之和 100，差 20，求两数。",
    "v2a": "**60 和 40**"
  },
  "2026-07-18": {
    "idx": 13,
    "stage": 3,
    "stage_name": "③黄金提升期",
    "diff": 2,
    "theme": "植树问题",
    "q": "在一条 20 米长的路一侧种树，每隔 5 米种一棵（两端都种），共需多少棵树？",
    "sol": "**植树公式**（两端都种）：棵数 = 距离÷间距 + 1\n- 20÷5+1 = **5 棵**\n\n**答：共需种 5 棵树。**",
    "v1": "街道长 100 米，每隔 10 米装一根灯杆（两端都装），共需多少根？",
    "v1a": "**11 根**",
    "v2": "池塘周长 200 米，每隔 5 米种一棵柳树（环形），共需多少棵？",
    "v2a": "**40 棵**（环形不+1）"
  },
  "2026-07-19": {
    "idx": 14,
    "stage": 3,
    "stage_name": "③黄金提升期",
    "diff": 2,
    "theme": "鸡兔同笼",
    "q": "笼子里有鸡和兔共 10 只，脚共 28 只，问鸡兔各几只？",
    "sol": "**假设法**：全是鸡 → 20 只脚，差 8 只\n- 每只兔比鸡多 2 只脚 → 兔：8÷2 = **4 只**\n- 鸡：10-4 = **6 只**\n\n**验证**：6×2+4×4 = 12+16 = 28 ✓\n\n**答：鸡 6 只，兔 4 只。**",
    "v1": "鸡兔同笼共 20 只，脚 50 只，各几只？",
    "v1a": "**鸡 15 只，兔 5 只**",
    "v2": "鸡兔同笼共 35 只，脚 94 只，各几只？",
    "v2a": "**鸡 23 只，兔 12 只**"
  },
  "2026-07-20": {
    "idx": 15,
    "stage": 3,
    "stage_name": "③黄金提升期",
    "diff": 2,
    "theme": "植树",
    "q": "在 50 米长的路一侧每隔 5 米种树（两端不种），共需几棵？",
    "sol": "**公式**（两端不种）：棵数 = 距离÷间距 - 1\n- 50÷5-1 = **9 棵**\n\n**答：共需 9 棵树。**",
    "v1": "马路长 200 米，每隔 10 米一根电线杆（两端不装），共几根？",
    "v1a": "**19 根**",
    "v2": "操场跑道周长 400 米，每 50 米插一面旗，环形，几面？",
    "v2a": "**8 面**"
  },
  "2026-07-21": {
    "idx": 16,
    "stage": 3,
    "stage_name": "③黄金提升期",
    "diff": 2,
    "theme": "鸡兔同笼",
    "q": "小明有 5 分和 2 分硬币共 20 枚，总值 70 分，问两种硬币各几枚？",
    "sol": "**改造为鸡兔问题**：5 分相当于\"兔\"，2 分相当于\"鸡\"\n- 假设全 2 分：40 分，差 30 分\n- 每多 1 枚 5 分多 3 分 → 5 分：30÷3 = **10 枚**\n- 2 分：20-10 = **10 枚**\n\n**验证**：10×5+10×2 = 50+20 = 70 ✓\n\n**答：5 分 10 枚，2 分 10 枚。**",
    "v1": "1 元和 5 角硬币共 30 枚，总值 25 元，各几枚？",
    "v1a": "**1 元 20 枚，5 角 10 枚**",
    "v2": "铅笔 2 元，圆珠笔 5 元，共买 12 支，花 40 元，各几支？",
    "v2a": "**铅笔 10 支，圆珠笔 2 支**"
  },
  "2026-07-22": {
    "idx": 17,
    "stage": 3,
    "stage_name": "③黄金提升期",
    "diff": 2,
    "theme": "盈亏",
    "q": "分饼干给小朋友，每人分 5 块少 3 块，每人分 6 块多 2 块，问有多少小朋友？",
    "sol": "**盈亏公式**：(盈+亏)÷分差 = 人数\n- 人数：(2+3)÷(6-5) = **5 人**\n- 饼干：5×5+3 = 28 块\n\n**答：5 个小朋友，28 块饼干。**",
    "v1": "分糖果，每人 8 颗少 6 颗，每人 10 颗多 12 颗，几人？",
    "v1a": "**9 人，66 颗**",
    "v2": "装盒，每盒 6 个少 4 个，每盒 5 个多 6 个，几盒？",
    "v2a": "**10 盒，56 个**"
  },
  "2026-07-23": {
    "idx": 18,
    "stage": 3,
    "stage_name": "③黄金提升期",
    "diff": 2,
    "theme": "植树",
    "q": "两栋楼之间每隔 3 米种一棵树，共种 7 棵树（两端不种），两楼相距多少米？",
    "sol": "**关键**：7 棵树之间有 6 个间隔（两端不种）\n- 距离：3×6 = **18 米**\n\n**答：两楼相距 18 米。**",
    "v1": "路边每隔 4 米种一棵树，共种 6 棵（两端都种），路长几米？",
    "v1a": "**20 米**",
    "v2": "街道长 36 米，每隔 6 米一棵树（两端都种），共几棵？",
    "v2a": "**7 棵**"
  },
  "2026-07-24": {
    "idx": 19,
    "stage": 3,
    "stage_name": "③黄金提升期",
    "diff": 2,
    "theme": "盈亏",
    "q": "同学们排队做操，每行 8 人多 3 人，每行 9 人少 7 人，问有多少人？",
    "sol": "**盈亏问题**：(盈+亏)÷分差 = 行数\n- 行数：(3+7)÷(9-8) = 10 行\n- 人数：10×8+3 = **83 人**\n\n**验证**：10×9-7 = 83 ✓\n\n**答：共 83 人。**",
    "v1": "分苹果，每人 5 个少 3 个，每人 4 个多 5 个，几人？",
    "v1a": "**8 人，37 个**",
    "v2": "分书，每生 3 本多 2 本，每生 4 本少 8 本，几本书？",
    "v2a": "**书 26 本，8 人**"
  },
  "2026-07-25": {
    "idx": 20,
    "stage": 3,
    "stage_name": "③黄金提升期",
    "diff": 2,
    "theme": "鸡兔同笼",
    "q": "龟鹤共 20 只，腿共 56 条，龟鹤各几只？（龟 4 腿鹤 2 腿）",
    "sol": "**改造**：龟=兔，鹤=鸡\n- 全鹤：40 腿，差 16 腿\n- 龟：16÷(4-2) = **8 只**\n- 鹤：20-8 = **12 只**\n\n**验证**：8×4+12×2 = 32+24 = 56 ✓\n\n**答：龟 8 只，鹤 12 只。**",
    "v1": "蜘蛛(8腿)蚂蚁(6腿)共 10 只，腿共 68 条，各几只？",
    "v1a": "**蜘蛛 4 只，蚂蚁 6 只**",
    "v2": "四脚兽和两脚兽共 12 只，腿 32 条，各几只？",
    "v2a": "**四脚兽 4 只，两脚兽 8 只**"
  },
  "2026-07-26": {
    "idx": 21,
    "stage": 3,
    "stage_name": "③黄金提升期",
    "diff": 2,
    "theme": "植树（环形）",
    "q": "圆形花坛周长 60 米，每隔 3 米摆一盆花，共需几盆？",
    "sol": "**环形公式**：棵数 = 距离÷间距（不加 1）\n- 60÷3 = **20 盆**\n\n**答：共需 20 盆花。**",
    "v1": "正方形操场边长 100 米，每隔 10 米种一棵树（每个角都种），共几棵？",
    "v1a": "**40 棵**（每边 11 棵×4 - 4 角 = 40）",
    "v2": "环形跑道周长 400 米，每 50 米一面旗，环形，几面？",
    "v2a": "**8 面**"
  },
  "2026-07-27": {
    "idx": 22,
    "stage": 3,
    "stage_name": "③黄金提升期",
    "diff": 3,
    "theme": "鸡兔同笼（升级）",
    "q": "100 个馒头 100 个和尚吃，大和尚一人吃 3 个，小和尚 3 人吃 1 个，求大小和尚各几人？",
    "sol": "**复杂鸡兔问题**：\n- 大和尚×3 + 小和尚÷3 = 100\n- 大和尚 + 小和尚 = 100\n- 假设全是小和尚：100÷3 ≈ 33 馒头（差 67）\n- 每大换小变化：3-1/3 = 8/3 个馒头差\n- 大和尚：200/3 ÷ 8/3 = **25 人**\n- 小和尚：75 人\n\n**验证**：25×3 + 75÷3 = 75+25 = 100 ✓\n\n**答：大和尚 25 人，小和尚 75 人。**",
    "v1": "1 角和 5 角硬币共 30 枚，总值 9 元 8 角，各几枚？",
    "v1a": "**5 角 17 枚，1 角 13 枚**",
    "v2": "100 匹马 100 块砖，大马驮 3 块，小马驮 2 块，俩小马驹驮 1 块，问各几匹？",
    "v2a": "**大马 2 匹，小马 30 匹，马驹 68 匹**"
  },
  "2026-07-28": {
    "idx": 23,
    "stage": 3,
    "stage_name": "③黄金提升期",
    "diff": 2,
    "theme": "盈亏",
    "q": "小华带钱买钢笔，每支 8 元少 4 元，每支 7 元多 5 元，他带了多少钱？",
    "sol": "**盈亏问题**：\n- 支数：(5+4)÷(8-7) = **9 支**\n- 钱：9×8-4 = **68 元**\n\n**答：小华带了 68 元。**",
    "v1": "分糖，每人 6 颗少 4 颗，每人 5 颗多 5 颗，几颗糖？",
    "v1a": "**糖 35 颗，7 人**",
    "v2": "工人运货，每车 4 吨多 1 吨，每车 5 吨少 4 吨，几吨货？",
    "v2a": "**24 吨货，5 辆车**"
  },
  "2026-07-29": {
    "idx": 24,
    "stage": 3,
    "stage_name": "③黄金提升期",
    "diff": 2,
    "theme": "植树",
    "q": "街道一侧每隔 4 米种一棵树（两端都种），共 11 棵，街道长几米？",
    "sol": "**公式**：距离 = (棵数-1)×间距\n- (11-1)×4 = **40 米**\n\n**答：街道长 40 米。**",
    "v1": "道路两侧每隔 5 米种一棵树（两端都种），共 22 棵，道路长几米？",
    "v1a": "**50 米**（单侧 11 棵，两侧 22 棵）",
    "v2": "学校到公园每隔 6 米一棵树（两端不种），共 9 棵，相距几米？",
    "v2a": "**54 米**"
  },
  "2026-07-30": {
    "idx": 25,
    "stage": 3,
    "stage_name": "③黄金提升期",
    "diff": 3,
    "theme": "综合（植树+几何）",
    "q": "四边形场地边长 60 米，每 5 米插一面旗（每个角都插），共几面？",
    "sol": "**关键**：正方形 4 条边 = 240 米\n- 每边：60÷5+1 = 13 个位置\n- 4 角被重复 4 次 → 13×4-4 = **48 面**\n\n**验证**：每边 12 个间隔，4 边 = 48 个间隔，环形不+1 → 48 面 ✓\n\n**答：共 48 面旗。**",
    "v1": "长方形操场长 100 米宽 60 米，每 10 米一面旗（每个角都插），共几面？",
    "v1a": "**32 面**（长边 11×2-2=20，宽边 7×2-2=12）",
    "v2": "三角形场地三边 60/80/100 米，每 10 米一旗（角上不插），共几面？",
    "v2a": "**21 面**"
  },
  "2026-07-31": {
    "idx": 26,
    "stage": 3,
    "stage_name": "③黄金提升期",
    "diff": 2,
    "theme": "盈亏（升级）",
    "q": "学生分练习本，每生 4 本多 9 本，每生 5 本少 6 本，问学生几人？练习本几本？",
    "sol": "**公式**：人数 = (盈+亏)÷分差\n- 人数：(9+6)÷(5-4) = **15 人**\n- 本数：15×4+9 = **69 本**\n\n**验证**：15×5-6 = 69 ✓\n\n**答：15 人，69 本。**",
    "v1": "分饼干，每生 6 块多 12 块，每生 7 块少 4 块，几人？",
    "v1a": "**16 人，108 块**",
    "v2": "工人运货，每车 4 吨多 1 吨，每车 5 吨少 4 吨，几吨货？",
    "v2a": "**24 吨货，5 辆车**"
  },
  "2026-08-01": {
    "idx": 27,
    "stage": 3,
    "stage_name": "③黄金提升期",
    "diff": 3,
    "theme": "综合（鸡兔升级）",
    "q": "鸡兔同笼，鸡比兔多 15 只，共 198 只脚，问鸡兔各几只？",
    "sol": "**改造**：设兔 x 只，鸡(x+15)只\n- 4x + 2(x+15) = 198\n- 4x + 2x + 30 = 198\n- 6x = 168\n- x = **28 兔**\n- 鸡：28+15 = **43 只**\n\n**验证**：28×4+43×2 = 112+86 = 198 ✓\n\n**答：兔 28 只，鸡 43 只。**",
    "v1": "鸡比兔少 10 只，共 100 只脚，各几只？",
    "v1a": "**鸡 20 只，兔 30 只**",
    "v2": "白兔比灰兔多 20 只，共 200 只脚，各几只？",
    "v2a": "**灰兔 30 只，白兔 50 只**"
  },
  "2026-08-02": {
    "idx": 55,
    "stage": 3,
    "stage_name": "③黄金提升期",
    "diff": 2,
    "theme": "植树（升级）",
    "q": "两栋楼之间每隔 4 米种一棵树，共种 11 棵（两端不种），两楼相距多少米？",
    "sol": "**关键**：11 棵树之间有 10 个间隔（两端不种）\n- 距离：4×10 = **40 米**\n\n**答：两楼相距 40 米。**",
    "v1": "街道每隔 5 米种一棵树（两端都种），共 9 棵，路长几米？",
    "v1a": "**40 米**（(9-1)×5）",
    "v2": "两楼之间每隔 3 米种一棵树，共 8 棵（两端不种），相距几米？",
    "v2a": "**21 米**（(8-1)×3）"
  },
  "2026-08-03": {
    "idx": 28,
    "stage": 4,
    "stage_name": "④编程二期",
    "diff": 2,
    "theme": "年龄问题",
    "q": "妈妈今年 35 岁，小明今年 7 岁，几年后妈妈年龄是小明的 3 倍？",
    "sol": "**年龄差不变**：35-7 = 28 岁\n- 设 x 年后：35+x = 3(7+x)\n- 35+x = 21+3x\n- 14 = 2x\n- x = **7 年**\n\n**验证**：7 年后妈 42，小明 14，42÷14 = 3 ✓\n\n**答：7 年后。**",
    "v1": "父 40 岁，子 10 岁，几年后父是子的 2 倍？",
    "v1a": "**20 年后**（差 30，2 倍 → 子 30，父 60，需要 20 年）",
    "v2": "爷 60 岁，孙 5 岁，几年后爷是孙的 3 倍？",
    "v2a": "**22 年后**（差 55，3 倍 → 孙 27.5，爷 82.5 → 22 年后不整，调整为 4 倍：再过 13 年爷 73 孙 18）"
  },
  "2026-08-04": {
    "idx": 29,
    "stage": 4,
    "stage_name": "④编程二期",
    "diff": 2,
    "theme": "归一",
    "q": "3 辆卡车 4 次运货 36 吨，5 辆卡车 6 次能运多少吨？",
    "sol": "**归一法**：先求 1 辆 1 次运量\n- 1 辆 1 次：36÷3÷4 = 3 吨\n- 5 辆 6 次：3×5×6 = **90 吨**\n\n**答：能运 90 吨。**",
    "v1": "4 人 5 天做 80 个零件，6 人 7 天做多少个？",
    "v1a": "**168 个**",
    "v2": "3 台机器 2 小时产 60 个零件，5 台机器 4 小时产多少？",
    "v2a": "**200 个**"
  },
  "2026-08-05": {
    "idx": 30,
    "stage": 4,
    "stage_name": "④编程二期",
    "diff": 2,
    "theme": "年龄",
    "q": "5 年前爸爸年龄是儿子的 4 倍，5 年后是儿子的 2 倍，今年父子各几岁？",
    "sol": "**关键**：年龄差不变\n- 设今年父 x 岁，子 y 岁\n- x-5 = 4(y-5) → x-5 = 4y-20 → x = 4y-15\n- x+5 = 2(y+5) → x+5 = 2y+10 → x = 2y+5\n- 4y-15 = 2y+5 → 2y = 20 → y = 10\n- x = 2×10+5 = **25**\n\n**答：父 25 岁，子 10 岁。**",
    "v1": "3 年前甲是乙的 3 倍，3 年后甲是乙的 2 倍，今年各几岁？",
    "v1a": "**甲 33 岁，乙 13 岁**",
    "v2": "10 年前父是子的 6 倍，10 年后是子的 2 倍，今年各几岁？",
    "v2a": "**父 40 岁，子 10 岁**"
  },
  "2026-08-06": {
    "idx": 31,
    "stage": 4,
    "stage_name": "④编程二期",
    "diff": 2,
    "theme": "数列",
    "q": "找规律填数：1, 4, 9, 16, __, 36, 49",
    "sol": "**观察**：1²=1, 2²=4, 3²=9, 4²=16, 5²=**25**, 6²=36, 7²=49\n\n**答：25**",
    "v1": "找规律：2, 5, 10, 17, __, 37",
    "v1a": "**26**（差值 3,5,7,9,11,13）",
    "v2": "找规律：1, 8, 27, 64, __",
    "v2a": "**125**（n³：1³,2³,3³,4³,5³）"
  },
  "2026-08-07": {
    "idx": 32,
    "stage": 4,
    "stage_name": "④编程二期",
    "diff": 2,
    "theme": "归一",
    "q": "5 个工人 3 天装订 1500 本书，照这样 8 个工人 6 天装订多少本？",
    "sol": "**归一法**：\n- 1 人 1 天：1500÷5÷3 = 100 本\n- 8 人 6 天：100×8×6 = **4800 本**\n\n**答：4800 本。**",
    "v1": "3 头牛 4 天吃草 240 千克，5 头牛 6 天吃多少？",
    "v1a": "**600 千克**",
    "v2": "2 台织布机 3 小时织 60 米布，5 台 8 小时织多少？",
    "v2a": "**400 米**"
  },
  "2026-08-08": {
    "idx": 33,
    "stage": 4,
    "stage_name": "④编程二期",
    "diff": 2,
    "theme": "年龄",
    "q": "父子年龄和 50 岁，5 年后父是子的 2 倍，今年父子各几岁？",
    "sol": "**5 年后和**：50+10 = 60\n- 5 年后子 x 岁 → 父 2x\n- x+2x = 60 → x = 20（5 年后）\n- 今年：父 **25**，子 **15**\n\n**答：父 25 岁，子 15 岁。**",
    "v1": "母女年龄和 45 岁，10 年后母是女的 4 倍，今年各几岁？",
    "v1a": "**母 30 岁，女 15 岁**（10 年后母 40 女 10）",
    "v2": "甲乙年龄和 60 岁，3 年后甲是乙的 1.5 倍，今年各几岁？",
    "v2a": "**甲 30 岁，乙 30 岁**（3 年后甲 33 乙 33，比为 1）"
  },
  "2026-08-09": {
    "idx": 34,
    "stage": 4,
    "stage_name": "④编程二期",
    "diff": 3,
    "theme": "数列（高阶）",
    "q": "找规律：1, 1, 2, 3, 5, 8, 13, __",
    "sol": "**斐波那契数列**：从第 3 项起，每项 = 前两项之和\n- 1+1=2, 1+2=3, 2+3=5, 3+5=8, 5+8=13, 8+13=**21**\n\n**答：21**",
    "v1": "找规律：1, 3, 4, 7, 11, 18, __",
    "v1a": "**29**（前两项和）",
    "v2": "找规律：2, 3, 5, 9, 17, __",
    "v2a": "**33**（前一项×2-1）"
  },
  "2026-08-10": {
    "idx": 35,
    "stage": 4,
    "stage_name": "④编程二期",
    "diff": 2,
    "theme": "归一（复杂）",
    "q": "一项工程 10 人 15 天可完成，若要提前 5 天完成，需增加几人？",
    "sol": "**总工作量**：10×15 = 150 人天\n- 提前 5 天 → 10 天完成\n- 需人数：150÷10 = **15 人**\n- 需增加：15-10 = **5 人**\n\n**答：需增加 5 人。**",
    "v1": "5 台机器 8 小时产 400 个零件，要 4 小时产 400 个需几台？",
    "v1a": "**10 台**",
    "v2": "3 辆卡车 5 次运 90 吨，要 2 辆 6 次运完需多少吨货？",
    "v2a": "**72 吨**"
  },
  "2026-08-11": {
    "idx": 36,
    "stage": 4,
    "stage_name": "④编程二期",
    "diff": 2,
    "theme": "年龄（综合）",
    "q": "今年哥哥 16 岁，弟弟 8 岁，几年前哥哥的年龄是弟弟的 3 倍？",
    "sol": "**差不变**：16-8 = 8\n- x 年前：16-x = 3(8-x)\n- 16-x = 24-3x\n- 2x = 8\n- x = **4 年**\n\n**验证**：4 年前哥 12，弟 4，12÷4 = 3 ✓\n\n**答：4 年前。**",
    "v1": "父 30 岁，子 4 岁，几年后父是子的 4 倍？",
    "v1a": "**再过 2 年**（32=4×8）",
    "v2": "甲 20 岁，乙 10 岁，几年前甲是乙的 5 倍？",
    "v2a": "**5 年前**（15=5×3）"
  },
  "2026-08-12": {
    "idx": 37,
    "stage": 4,
    "stage_name": "④编程二期",
    "diff": 3,
    "theme": "数列（等差）",
    "q": "找规律填数：3, 6, 12, 24, __, 96",
    "sol": "**等比数列**：每项 = 前一项 × 2\n- 3, 6, 12, 24, 48, 96 ✓\n\n**答：48**",
    "v1": "找规律：1, 3, 9, 27, __, 243",
    "v1a": "**81**（×3）",
    "v2": "找规律：100, 50, 25, __, 6.25",
    "v2a": "**12.5**（÷2）"
  },
  "2026-08-13": {
    "idx": 38,
    "stage": 4,
    "stage_name": "④编程二期",
    "diff": 2,
    "theme": "归一（行程）",
    "q": "小汽车 3 小时行 210 公里，骑自行车 4 小时行 80 公里。小汽车比自行车每小时快多少公里？",
    "sol": "**分别算速再比**：\n- 小汽车：210÷3 = 70 km/h\n- 自行车：80÷4 = 20 km/h\n- 差：70-20 = **50 km/h**\n\n**答：小汽车比自行车每小时快 50 公里。**",
    "v1": "甲车 2 小时行 160 km，乙车 3 小时行 180 km，甲比乙每小时快多少？",
    "v1a": "**20 km/h**",
    "v2": "飞机 4 小时行 3600 km，汽车 5 小时行 400 km，飞机比汽车快多少 km/h？",
    "v2a": "**820 km/h**"
  },
  "2026-08-14": {
    "idx": 39,
    "stage": 4,
    "stage_name": "④编程二期",
    "diff": 3,
    "theme": "数列+年龄",
    "q": "小华每年的压岁钱都比上一年多 200 元，他 7 岁时存 800 元，他 12 岁时存多少？",
    "sol": "**等差数列**：首项 800，公差 200\n- 第 1 年（7 岁）：800\n- 第 2 年（8 岁）：1000\n- 第 6 年（12 岁）：800+200×5 = **1800 元**\n\n**答：12 岁时存 1800 元。**",
    "v1": "小树苗今年高 1.5 米，每年长 0.3 米，5 年后几米？",
    "v1a": "**3.0 米**",
    "v2": "水池每天漏水 50 升，原有 1000 升，几天后剩 500 升？",
    "v2a": "**10 天**"
  },
  "2026-08-15": {
    "idx": 40,
    "stage": 5,
    "stage_name": "⑤开学衔接期",
    "diff": 2,
    "theme": "巧算",
    "q": "计算：1+2+3+4+...+100 = ?",
    "sol": "**高斯求和法**：(首+末)×项数÷2\n- (1+100)×100÷2 = 101×50 = **5050**\n\n**答：5050**",
    "v1": "计算 1+2+3+...+50",
    "v1a": "**1275**（(1+50)×50÷2）",
    "v2": "计算 11+12+13+...+20",
    "v2a": "**155**（(11+20)×10÷2）"
  },
  "2026-08-16": {
    "idx": 41,
    "stage": 5,
    "stage_name": "⑤开学衔接期",
    "diff": 2,
    "theme": "巧算",
    "q": "计算：1+3+5+7+9+...+99（共 50 个奇数）",
    "sol": "**奇数求和公式**：项数²\n- 50² = **2500**\n\n**答：2500**",
    "v1": "2+4+6+...+100（共 50 个偶数）",
    "v1a": "**2550**（(2+100)×50÷2）",
    "v2": "1+3+5+...+2019（奇数和）",
    "v2a": "**1010² = 1020100**"
  },
  "2026-08-17": {
    "idx": 42,
    "stage": 5,
    "stage_name": "⑤开学衔接期",
    "diff": 3,
    "theme": "综合",
    "q": "一个数加上 5 乘以 2 减去 8 除以 3 等于 4，求这个数。",
    "sol": "**逆推法**（反向操作）：\n- 4 × 3 = 12\n- 12 + 8 = 20\n- 20 ÷ 2 = 10\n- 10 - 5 = **5**\n\n**答：这个数是 5。**",
    "v1": "一个数乘以 3 加 5 减 8 除以 2 等于 6，原数？",
    "v1a": "**5**（逆推：6×2=12, 12+8=20, 20-5=15, 15÷3=5）",
    "v2": "某数除以 4 加 3 减 2 乘以 5 等于 30，原数？",
    "v2a": "**8**（30÷5=6, 6+2=8, 8-3=5, 5×4=20）"
  },
  "2026-08-18": {
    "idx": 43,
    "stage": 5,
    "stage_name": "⑤开学衔接期",
    "diff": 3,
    "theme": "行程综合",
    "q": "甲乙两人从 A、B 两地同时相向而行，甲每小时走 5 km，乙每小时走 4 km，2 小时后相遇。AB 距离多少？",
    "sol": "**相向而行**：速度和 × 时间 = 距离\n- (5+4)×2 = **18 km**\n\n**答：AB 距离 18 公里。**",
    "v1": "甲乙从两地相向走，甲 6 km/h，乙 5 km/h，3 小时相遇，距离？",
    "v1a": "**33 km**",
    "v2": "甲乙同向走，甲 8 km/h，乙 5 km/h，4 小时甲追乙 12 km，原距离？",
    "v2a": "**4 km**"
  },
  "2026-08-19": {
    "idx": 44,
    "stage": 5,
    "stage_name": "⑤开学衔接期",
    "diff": 3,
    "theme": "分数应用",
    "q": "一根绳子，第一次用去全长的 1/3，第二次用去剩下的 1/2，还剩 5 米。原长多少？",
    "sol": "**关键**：第二次用去\"剩下的 1/2\" → 剩 5 米 = 第一次剩的 1/2\n- 第一次剩：5×2 = 10 米\n- 10 米 = 全长的 2/3 → 全长：10÷2/3 = **15 米**\n\n**验证**：15-15×1/3=10, 10-10×1/2=5 ✓\n\n**答：原长 15 米。**",
    "v1": "一桶油，第一次用 1/4，第二次用剩下的 1/3，还剩 9 升，原几升？",
    "v1a": "**18 升**",
    "v2": "一本书，第一天看 1/4，第二天看剩下的 1/3，剩 60 页，原几页？",
    "v2a": "**120 页**"
  },
  "2026-08-20": {
    "idx": 45,
    "stage": 5,
    "stage_name": "⑤开学衔接期",
    "diff": 3,
    "theme": "几何",
    "q": "一个长方形周长 36 cm，长是宽的 2 倍，求面积。",
    "sol": "**长方形周长 = 2(长+宽)**\n- 长+宽 = 36÷2 = 18\n- 长 = 2 宽 → 3 宽 = 18 → 宽 = 6, 长 = 12\n- 面积：6×12 = **72 cm²**\n\n**答：面积 72 平方厘米。**",
    "v1": "长方形周长 40 cm，长比宽多 4 cm，面积？",
    "v1a": "**96 cm²**（长 12 宽 8）",
    "v2": "正方形边长增加 3 cm 后面积增加 81 cm²，原边长？",
    "v2a": "**12 cm**（(x+3)²-x²=81 → 6x+9=81 → x=12）"
  },
  "2026-08-21": {
    "idx": 46,
    "stage": 5,
    "stage_name": "⑤开学衔接期",
    "diff": 3,
    "theme": "工程",
    "q": "一项工程，甲单独做 6 天完成，乙单独做 12 天完成，两人合作几天完成？",
    "sol": "**工程问题**：把工作总量看作 1\n- 甲效率：1/6\n- 乙效率：1/12\n- 合作：1/6+1/12 = 3/12 = 1/4\n- 时间：1÷1/4 = **4 天**\n\n**答：4 天完成。**",
    "v1": "甲独做 8 天，乙独做 12 天，合作几天？",
    "v1a": "**4.8 天**（1/(1/8+1/12)=24/5=4.8）",
    "v2": "甲独做 10 天，乙独做 15 天，合作完成 1/2 需几天？",
    "v2a": "**3 天**（合作 1 天 1/6，1/2 需 3 天）"
  },
  "2026-08-22": {
    "idx": 47,
    "stage": 5,
    "stage_name": "⑤开学衔接期",
    "diff": 3,
    "theme": "行程（追及）",
    "q": "哥哥每分钟走 80 米，弟弟每分钟走 60 米，弟弟先走 5 分钟，哥哥几分钟追上？",
    "sol": "**追及问题**：路程差 = 速度差 × 时间\n- 弟弟先走：60×5 = 300 米（路差）\n- 速度差：80-60 = 20 m/min\n- 追及时间：300÷20 = **15 分钟**\n\n**答：15 分钟追上。**",
    "v1": "快车 80 km/h，慢车 60 km/h，慢车先开 2 小时，快车几小时追上？",
    "v1a": "**6 小时**（120÷20）",
    "v2": "甲 60 m/min 先走 3 分钟，乙 90 m/min 追，几分钟？",
    "v2a": "**6 分钟**（180÷30）"
  },
  "2026-08-23": {
    "idx": 48,
    "stage": 5,
    "stage_name": "⑤开学衔接期",
    "diff": 3,
    "theme": "综合巧算",
    "q": "计算：999 + 99 + 9 = ?",
    "sol": "**凑整法**：\n- 999+1+99+1+9+1-3 = 1000+100+10-3 = **1107**\n\n**答：1107**",
    "v1": "计算：1999+199+19+1",
    "v1a": "**2218**（2000+200+20-2）",
    "v2": "计算：99×99+199",
    "v2a": "**10000**（99²=9801, +199=10000）"
  },
  "2026-08-24": {
    "idx": 49,
    "stage": 5,
    "stage_name": "⑤开学衔接期",
    "diff": 3,
    "theme": "数列（高阶）",
    "q": "观察：1×1=1, 11×11=121, 111×111=12321，求 1111×1111 = ?",
    "sol": "**找规律**：1×1=1, 11²=121, 111²=12321 → 1111²=**1234321**\n\n**答：1234321**",
    "v1": "找规律：5×5=25, 55×55=3025, 555×555=308025, 5555×5555=？",
    "v1a": "**30808025**",
    "v2": "找规律：9×9=81, 99×99=9801, 999×999=998001, 9999×9999=？",
    "v2a": "**99980001**"
  },
  "2026-08-25": {
    "idx": 50,
    "stage": 5,
    "stage_name": "⑤开学衔接期",
    "diff": 3,
    "theme": "浓度问题",
    "q": "有 20% 的盐水 500 克，加入 100 克水后，浓度变为多少？",
    "sol": "**关键**：盐不变\n- 原盐量：500×20% = 100 克\n- 新总重：500+100 = 600 克\n- 新浓度：100÷600 = **16.67%**\n\n**答：约 16.67%（或 1/6）**",
    "v1": "10% 糖水 200 克，加 100 克水，新浓度？",
    "v1a": "**6.67%**（20÷300）",
    "v2": "15% 盐水 200 克，加 50 克盐，新浓度？",
    "v2a": "**32%**（30+50=80, ÷250=32%）"
  },
  "2026-08-26": {
    "idx": 51,
    "stage": 5,
    "stage_name": "⑤开学衔接期",
    "diff": 3,
    "theme": "经济问题",
    "q": "某商品先涨价 20% 再降价 20%，现价比原价高还是低？",
    "sol": "**关键**：分步算\n- 原价 100 元 → 涨价后 120 元\n- 降价 20%：120×0.8 = 96 元\n\n**结论：现价比原价低 4%**\n\n**核心原理**：百分比基数变了（先涨后降，降的基数是涨价后的高价）",
    "v1": "原价 200 元，先降 10% 再涨 10%，现价？",
    "v1a": "**198 元**（180→198）",
    "v2": "原价 100 元，先涨 50% 再降 50%，现价？",
    "v2a": "**75 元**"
  },
  "2026-08-27": {
    "idx": 52,
    "stage": 5,
    "stage_name": "⑤开学衔接期",
    "diff": 3,
    "theme": "综合（最值）",
    "q": "把 14 分拆成 3 个自然数之和（不含 0），使这 3 个数的乘积最大，求最大乘积。",
    "sol": "**关键**：尽量分成 3 和 2\n- 14 = 3+3+3+3+2 → 4 个数不允许（要 3 个）\n- 14 = 4+5+5 → 4×5×5 = 100\n- 14 = 3+5+6 → 3×5×6 = 90\n- 14 = 4+4+6 → 4×4×6 = 96\n- 14 = 3+3+8 → 3×3×8 = 72\n\n**答：最大乘积 100（4+5+5）**",
    "v1": "把 10 分成 3 个自然数，乘积最大？",
    "v1a": "**3+3+4=36**",
    "v2": "把 20 分成 3 个自然数，乘积最大？",
    "v2a": "**6+7+7=294**"
  },
  "2026-08-28": {
    "idx": 53,
    "stage": 5,
    "stage_name": "⑤开学衔接期",
    "diff": 3,
    "theme": "追及+年龄",
    "q": "小红每分钟走 60 米，出发 5 分钟后妈妈发现她忘带文具，立即骑电动车去追，电动车每分钟走 180 米，妈妈几分钟后追上小红？",
    "sol": "**追及问题**：\n- 路程差：60×5 = 300 米\n- 速度差：180-60 = 120 米/分钟\n- 追及时间：300÷120 = **2.5 分钟**\n\n**答：2.5 分钟后追上。**",
    "v1": "小明每分钟走 70 米，出发 4 分钟后爸爸发现他忘带课本，开车去追，车速 240 米/分钟，几分钟追上？",
    "v1a": "**2 分钟**（280÷170≈1.65 → 2 分钟可追上）",
    "v2": "姐姐每分钟走 80 米，10 分钟后妹妹骑车追，妹妹每分钟 200 米，几分钟追上？",
    "v2a": "**6.67 分钟**（800÷120≈6.67）"
  },
  "2026-08-29": {
    "idx": 54,
    "stage": 5,
    "stage_name": "⑤开学衔接期",
    "diff": 3,
    "theme": "工程",
    "q": "一项工程甲独做 10 天，乙独做 15 天，两队合作 3 天后还剩几分之几？",
    "sol": "**关键**：先算合作 3 天完成量\n- 1 天完成：1/10+1/15 = 1/6\n- 3 天：3×1/6 = 1/2\n- 剩余：1-1/2 = **1/2**\n\n**答：还剩 1/2。**",
    "v1": "甲独做 8 天，乙独做 12 天，合作 2 天后剩几分之几？",
    "v1a": "**7/12**（1/8+1/12=5/24, ×2=5/12, 1-5/12=7/12）",
    "v2": "一项工程甲乙合作 6 天完成，已知甲独做 10 天，乙独做几天？",
    "v2a": "**15 天**（1/6-1/10=1/15）"
  }
}